<PAMDataset>
  <Metadata>
    <MDI key="DataType">Generic</MDI>
  </Metadata>
  <Metadata domain="Esri">
    <MDI key="PyramidResamplingType">NEAREST</MDI>
  </Metadata>
  <PAMRasterBand band="1">
    <Histograms>
      <HistItem>
        <HistMin>0</HistMin>
        <HistMax>0.4464686673836138</HistMax>
        <BucketCount>256</BucketCount>
        <IncludeOutOfRange>1</IncludeOutOfRange>
        <Approximate>0</Approximate>
        <HistCounts>88553|634|310|16330|63|73|178|396|1978|2677|26758|7615|8633|7770|8126|3420|4276|6308|4845|10520|16152|7135|6275|7602|7520|9770|8459|5744|11148|17864|12573|11703|8388|7009|6308|6167|6728|10164|10218|3611|1516|1291|1572|1637|2049|2562|1857|2558|3034|2939|2518|2501|2243|1659|1540|1493|1631|2116|2297|2612|3240|2038|1514|437|467|686|825|452|307|406|436|304|342|459|497|434|691|681|964|1085|1169|1516|2163|2586|1340|1416|1065|1149|1264|1500|1633|1365|1670|1440|1411|990|452|222|143|157|34|56|42|22|0|17|0|0|32|16|2|20|0|28|0|16|3|8|20|8|12|43|62|38|32|20|27|21|0|0|0|6|0|17|0|0|11|2|26|8|1|4|13|0|0|17|0|23|31|14|0|0|12|0|11|0|3|24|39|0|0|0|20|24|19|10|44|2|0|19|0|14|20|0|26|0|0|0|26|12|1|0|31|0|11|0|0|0|0|0|1|0|0|14|0|7|1|1|0|0|0|0|13|0|0|0|0|0|0|0|0|0|0|0|0|0|19|0|0|0|0|0|0|0|0|0|0|0|0|13|0|0|13|8|0|0|0|0|0|0|0|0|0|0|0|0|0|0|0|0|0|0|0|0|0|4</HistCounts>
      </HistItem>
    </Histograms>
    <Metadata>
      <MDI key="SourceBandIndex">0</MDI>
      <MDI key="STATISTICS_COVARIANCES">0.001719827155417153</MDI>
      <MDI key="STATISTICS_MAXIMUM">0.44646866738361</MDI>
      <MDI key="STATISTICS_MEAN">0.04602598064924</MDI>
      <MDI key="STATISTICS_MINIMUM">0</MDI>
      <MDI key="STATISTICS_SKIPFACTORX">1</MDI>
      <MDI key="STATISTICS_SKIPFACTORY">1</MDI>
      <MDI key="STATISTICS_STDDEV">0.041470798827816</MDI>
    </Metadata>
  </PAMRasterBand>
</PAMDataset>
